kitetdx/__init__.py
kitetdx/adjust.py
kitetdx/affair.py
kitetdx/downloader.py
kitetdx/entities/__init__.py
kitetdx/py_mini_racer_patch.py
kitetdx/quotes.py
kitetdx/reader.py
kitetdx/utils.py
kitetdx-0.1.13.dist-info/METADATA
kitetdx-0.1.13.dist-info/WHEEL
kitetdx-0.1.13.dist-info/licenses/LICENSE
kitetdx-0.1.13.dist-info/RECORD
