Metadata-Version: 2.4
Name: kitetdx
Version: 0.1.13
Summary: A custom wrapper and extension for mootdx.
License: MIT
License-File: LICENSE
Author: Kiteflyingee
Requires-Python: >=3.8,<4.0
Classifier: Development Status :: 2 - Pre-Alpha
Classifier: Intended Audience :: Developers
Classifier: License :: OSI Approved :: MIT License
Classifier: Natural Language :: English
Classifier: Programming Language :: Python :: 3
Classifier: Programming Language :: Python :: 3.8
Classifier: Programming Language :: Python :: 3.9
Classifier: Programming Language :: Python :: 3.10
Classifier: Programming Language :: Python :: 3.11
Classifier: Programming Language :: Python :: 3.12
Classifier: Programming Language :: Python :: 3.13
Classifier: Programming Language :: Python :: 3.14
Requires-Dist: click (>=8.1.3,<9.0.0)
Requires-Dist: httpx (>=0.25.0)
Requires-Dist: mootdx
Requires-Dist: prettytable (>=3.5.0,<4.0.0)
Requires-Dist: quickjs
Requires-Dist: selenium (>=4.15.0,<5.0.0)
Requires-Dist: tdxpy (>=0.2.5,<0.3.0)
Requires-Dist: tenacity (>=8.1.0,<9.0.0)
Requires-Dist: tqdm
Requires-Dist: typing-extensions (>=4.5.0,<5.0.0)
Requires-Dist: webdriver-manager (>=4.0.0,<5.0.0)
Project-URL: Homepage, https://github.com/Kiteflyingee/kitetdx
Project-URL: Repository, https://github.com/Kiteflyingee/kitetdx
